{
    "2022_WWZJetsTo4L2Nu": {
        "nleps_counts": [
            1488.0,
            null
        ],
        "njets_counts": [
            373.0,
            null
        ],
        "nbtagsl_counts": [
            63.0,
            null
        ],
        "sr_4l_sf_A_counts": [
            24.0,
            null
        ],
        "sr_4l_sf_B_counts": [
            20.0,
            null
        ],
        "sr_4l_sf_C_counts": [
            7.0,
            null
        ],
        "sr_4l_of_1_counts": [
            7.0,
            null
        ],
        "sr_4l_of_2_counts": [
            8.0,
            null
        ],
        "sr_4l_of_3_counts": [
            20.0,
            null
        ],
        "sr_4l_of_4_counts": [
            45.0,
            null
        ],
        "all_events_counts": [
            385.0,
            null
        ],
        "4l_presel_counts": [
            278.0,
            null
        ],
        "sr_4l_sf_counts": [
            51.0,
            null
        ],
        "sr_4l_of_counts": [
            80.0,
            null
        ],
        "sr_4l_sf_incl_counts": [
            52.0,
            null
        ],
        "sr_4l_of_incl_counts": [
            93.0,
            null
        ],
        "cr_4l_btag_of_counts": [
            8.0,
            null
        ],
        "cr_4l_btag_sf_offZ_met80_counts": [
            16.0,
            null
        ],
        "cr_4l_sf_counts": [
            9.0,
            null
        ],
        "cr_4l_btag_of_1b_counts": [
            8.0,
            null
        ],
        "cr_4l_btag_sf_offZ_met80_1b_counts": [
            14.0,
            null
        ],
        "cr_4l_btag_sf_offZ_met80_2b_counts": [
            2.0,
            null
        ],
        "sr_4l_bdt_sf_1_counts": [
            14.0,
            null
        ],
        "sr_4l_bdt_sf_2_counts": [
            10.0,
            null
        ],
        "sr_4l_bdt_sf_3_counts": [
            17.0,
            null
        ],
        "sr_4l_bdt_sf_4_counts": [
            13.0,
            null
        ],
        "sr_4l_bdt_sf_5_counts": [
            4.0,
            null
        ],
        "sr_4l_bdt_sf_6_counts": [
            3.0,
            null
        ],
        "sr_4l_bdt_sf_8_counts": [
            2.0,
            null
        ],
        "sr_4l_bdt_sf_coarse_1_counts": [
            24.0,
            null
        ],
        "sr_4l_bdt_sf_coarse_2_counts": [
            30.0,
            null
        ],
        "sr_4l_bdt_sf_coarse_3_counts": [
            7.0,
            null
        ],
        "sr_4l_bdt_sf_coarse_4_counts": [
            2.0,
            null
        ],
        "sr_4l_bdt_of_2_counts": [
            26.0,
            null
        ],
        "sr_4l_bdt_of_3_counts": [
            31.0,
            null
        ],
        "sr_4l_bdt_of_4_counts": [
            20.0,
            null
        ],
        "sr_4l_bdt_of_5_counts": [
            5.0,
            null
        ],
        "sr_4l_bdt_of_6_counts": [
            5.0,
            null
        ],
        "sr_4l_bdt_of_7_counts": [
            4.0,
            null
        ],
        "sr_4l_bdt_of_8_counts": [
            2.0,
            null
        ],
        "sr_4l_bdt_of_coarse_1_counts": [
            26.0,
            null
        ],
        "sr_4l_bdt_of_coarse_2_counts": [
            51.0,
            null
        ],
        "sr_4l_bdt_of_coarse_3_counts": [
            10.0,
            null
        ],
        "sr_4l_bdt_of_coarse_4_counts": [
            6.0,
            null
        ],
        "sr_4l_bdt_sf_wwz_counts": [
            54.0,
            null
        ],
        "sr_4l_bdt_sf_zh_counts": [
            9.0,
            null
        ],
        "sr_4l_bdt_of_wwz_counts": [
            77.0,
            null
        ],
        "sr_4l_bdt_of_zh_counts": [
            16.0,
            null
        ],
        "sr_4l_bdt_sf_presel_counts": [
            88.0,
            null
        ],
        "sr_4l_bdt_sf_trn_counts": [
            63.0,
            null
        ],
        "sr_4l_bdt_of_presel_counts": [
            93.0,
            null
        ],
        "sr_4l_bdt_of_trn_counts": [
            93.0,
            null
        ],
        "sr_4l_sf_A": [
            0.11246920221277315,
            null
        ],
        "sr_4l_sf_B": [
            0.12444773890612622,
            null
        ],
        "sr_4l_sf_C": [
            0.022766307478292044,
            null
        ],
        "sr_4l_of_1": [
            0.04155329110060785,
            null
        ],
        "sr_4l_of_2": [
            0.04441556671742743,
            null
        ],
        "sr_4l_of_3": [
            0.12005104684355504,
            null
        ],
        "sr_4l_of_4": [
            0.23468383750876526,
            null
        ],
        "all_events": [
            2.1740423090171324,
            null
        ],
        "4l_presel": [
            1.5211823607516586,
            null
        ],
        "sr_4l_sf": [
            0.2596832485971914,
            null
        ],
        "sr_4l_of": [
            0.44070374217035563,
            null
        ],
        "sr_4l_sf_incl": [
            0.269953094174741,
            null
        ],
        "sr_4l_of_incl": [
            0.4930925198816408,
            null
        ],
        "cr_4l_btag_of": [
            0.05362998119278961,
            null
        ],
        "cr_4l_btag_sf_offZ_met80": [
            0.07348691351092251,
            null
        ],
        "cr_4l_sf": [
            0.045745205334677394,
            null
        ],
        "cr_4l_btag_of_1b": [
            0.05362998119278961,
            null
        ],
        "cr_4l_btag_sf_offZ_met80_1b": [
            0.0649077676980758,
            null
        ],
        "cr_4l_btag_sf_offZ_met80_2b": [
            0.008579145812846715,
            null
        ],
        "sr_4l_bdt_sf_1": [
            0.05576102640184927,
            null
        ],
        "sr_4l_bdt_sf_2": [
            0.06693068659077164,
            null
        ],
        "sr_4l_bdt_sf_3": [
            0.0772599522859995,
            null
        ],
        "sr_4l_bdt_sf_4": [
            0.07637612024786593,
            null
        ],
        "sr_4l_bdt_sf_5": [
            0.024914860045731284,
            null
        ],
        "sr_4l_bdt_sf_6": [
            0.01773283108586001,
            null
        ],
        "sr_4l_bdt_sf_8": [
            0.013387113819054356,
            null
        ],
        "sr_4l_bdt_sf_coarse_1": [
            0.12269171299262091,
            null
        ],
        "sr_4l_bdt_sf_coarse_2": [
            0.1536360725338654,
            null
        ],
        "sr_4l_bdt_sf_coarse_3": [
            0.042647691131591295,
            null
        ],
        "sr_4l_bdt_sf_coarse_4": [
            0.013387113819054356,
            null
        ],
        "sr_4l_bdt_of_2": [
            0.13611188511942524,
            null
        ],
        "sr_4l_bdt_of_3": [
            0.14843585325296008,
            null
        ],
        "sr_4l_bdt_of_4": [
            0.10796535360939861,
            null
        ],
        "sr_4l_bdt_of_5": [
            0.027498047159176794,
            null
        ],
        "sr_4l_bdt_of_6": [
            0.04074778953624644,
            null
        ],
        "sr_4l_bdt_of_7": [
            0.023963901893650833,
            null
        ],
        "sr_4l_bdt_of_8": [
            0.00836968931078281,
            null
        ],
        "sr_4l_bdt_of_coarse_1": [
            0.13611188511942524,
            null
        ],
        "sr_4l_bdt_of_coarse_2": [
            0.25640120686235873,
            null
        ],
        "sr_4l_bdt_of_coarse_3": [
            0.06824583669542324,
            null
        ],
        "sr_4l_bdt_of_coarse_4": [
            0.032333591204433645,
            null
        ],
        "sr_4l_bdt_sf_wwz": [
            0.2763277855264863,
            null
        ],
        "sr_4l_bdt_sf_zh": [
            0.056034804950645646,
            null
        ],
        "sr_4l_bdt_of_wwz": [
            0.392513091981784,
            null
        ],
        "sr_4l_bdt_of_zh": [
            0.10057942789985688,
            null
        ],
        "sr_4l_bdt_sf_presel": [
            0.5134992645569546,
            null
        ],
        "sr_4l_bdt_sf_trn": [
            0.33236259047713196,
            null
        ],
        "sr_4l_bdt_of_presel": [
            0.4930925198816408,
            null
        ],
        "sr_4l_bdt_of_trn": [
            0.4930925198816408,
            null
        ]
    }
}